fasthooks/__init__.py
fasthooks/__main__.py
fasthooks/app.py
fasthooks/blueprint.py
fasthooks/logging.py
fasthooks/py.typed
fasthooks/registry.py
fasthooks/responses.py
fasthooks/_internal/__init__.py
fasthooks/_internal/io.py
fasthooks/cli/__init__.py
fasthooks/cli/app.py
fasthooks/cli/commands/__init__.py
fasthooks/cli/commands/init.py
fasthooks/cli/commands/install.py
fasthooks/cli/commands/status.py
fasthooks/cli/commands/uninstall.py
fasthooks/cli_utils/__init__.py
fasthooks/cli_utils/introspect.py
fasthooks/cli_utils/lock.py
fasthooks/cli_utils/paths.py
fasthooks/cli_utils/settings.py
fasthooks/cli_utils/validation.py
fasthooks/contrib/__init__.py
fasthooks/contrib/claude/__init__.py
fasthooks/contrib/claude/agent.py
fasthooks/depends/__init__.py
fasthooks/depends/state.py
fasthooks/depends/transcript.py
fasthooks/events/__init__.py
fasthooks/events/base.py
fasthooks/events/lifecycle.py
fasthooks/events/tools.py
fasthooks/observability/__init__.py
fasthooks/observability/backend.py
fasthooks/observability/base.py
fasthooks/observability/enums.py
fasthooks/observability/events.py
fasthooks/observability/observers/__init__.py
fasthooks/observability/observers/capture.py
fasthooks/observability/observers/file.py
fasthooks/observability/observers/sqlite.py
fasthooks/strategies/__init__.py
fasthooks/strategies/base.py
fasthooks/strategies/clean_state.py
fasthooks/strategies/long_running.py
fasthooks/strategies/registry.py
fasthooks/strategies/token_budget.py
fasthooks/studio/__init__.py
fasthooks/studio/__main__.py
fasthooks/studio/connection_manager.py
fasthooks/studio/server.py
fasthooks/studio/static/index.html
fasthooks/studio/static/vite.svg
fasthooks/studio/static/assets/index-0whJfhI5.js
fasthooks/studio/static/assets/index-DrLxTUWH.css
fasthooks/tasks/__init__.py
fasthooks/tasks/backend.py
fasthooks/tasks/base.py
fasthooks/tasks/depends.py
fasthooks/tasks/testing.py
fasthooks/testing/__init__.py
fasthooks/testing/client.py
fasthooks/testing/mocks.py
fasthooks-0.1.4.dist-info/METADATA
fasthooks-0.1.4.dist-info/WHEEL
fasthooks-0.1.4.dist-info/entry_points.txt
fasthooks-0.1.4.dist-info/RECORD
