Metadata-Version: 2.4
Name: fasthooks
Version: 0.1.4
Summary: Delightful Claude Code hooks - FastAPI-like DX for building hooks
Project-URL: Homepage, https://github.com/oneryalcin/fasthooks
Project-URL: Repository, https://github.com/oneryalcin/fasthooks
Project-URL: Issues, https://github.com/oneryalcin/fasthooks/issues
Author-email: Mehmet Oner Yalcin <oneryalcin@gmail.com>
Keywords: ai,anthropic,claude,cli,hooks
Requires-Python: >=3.11
Requires-Dist: anyio>=4.0
Requires-Dist: json5>=0.12.0
Requires-Dist: pydantic>=2.0
Requires-Dist: rich>=14.0
Requires-Dist: typer>=0.20.0
Provides-Extra: claude
Requires-Dist: claude-agent-sdk>=0.1.0; extra == 'claude'
Provides-Extra: studio
Requires-Dist: fastapi>=0.115.0; extra == 'studio'
Requires-Dist: uvicorn>=0.34.0; extra == 'studio'
Requires-Dist: websockets>=14.0; extra == 'studio'
